AnnoSpat/__init__.py
AnnoSpat/classify_IMCcells.py
AnnoSpat/pp.R
AnnoSpat/run.py
AnnoSpat/sample_Rscript.R
AnnoSpat/dependencies/cluster_cells.py
AnnoSpat/dependencies/helper_functions.py
AnnoSpat-1.0.0.dist-info/LICENSE
AnnoSpat-1.0.0.dist-info/METADATA
AnnoSpat-1.0.0.dist-info/WHEEL
AnnoSpat-1.0.0.dist-info/entry_points.txt
AnnoSpat-1.0.0.dist-info/top_level.txt
AnnoSpat-1.0.0.dist-info/RECORD
