Metadata-Version: 2.1
Name: AnnoSpat
Version: 1.0.0
Summary: A tool for annotating and inferring patterns in single cells from spatial proteomics
Home-page: https://github.com/aanchalMongia/AnnoSpat
Author: Aanchal Mongia
Author-email: aanchal.mongia@pennmedicine.upenn.edu
Classifier: Programming Language :: Python :: 3
Classifier: License :: OSI Approved :: MIT License
Classifier: Operating System :: OS Independent
Requires-Python: >=3.6
License-File: LICENSE
Requires-Dist: typer
Requires-Dist: numpy
Requires-Dist: scikit-learn
Requires-Dist: pandas
